matrepr/__init__.py
matrepr/base_formatter.py
matrepr/html.py
matrepr/html_formatter.py
matrepr/jupyter.py
matrepr/jupyter_html.py
matrepr/jupyter_latex.py
matrepr/latex.py
matrepr/latex_formatter.py
matrepr/list_converter.py
matrepr/string_formatter.py
matrepr/adapters/__init__.py
matrepr/adapters/graphblas_driver.py
matrepr/adapters/graphblas_impl.py
matrepr/adapters/list_like.py
matrepr/adapters/numpy_driver.py
matrepr/adapters/numpy_impl.py
matrepr/adapters/scipy_driver.py
matrepr/adapters/scipy_impl.py
matrepr/adapters/sparse_driver.py
matrepr/adapters/sparse_impl.py
matrepr/adapters/tensorflow_driver.py
matrepr/adapters/tensorflow_impl.py
matrepr/adapters/torch_driver.py
matrepr/adapters/torch_impl.py
matrepr/patch/__init__.py
matrepr/patch/graphblas.py
matrepr/patch/scipy.py
matrepr/patch/sparse.py
matrepr-1.0.1.dist-info/LICENSE.txt
matrepr-1.0.1.dist-info/METADATA
matrepr-1.0.1.dist-info/WHEEL
matrepr-1.0.1.dist-info/top_level.txt
matrepr-1.0.1.dist-info/RECORD
