Metadata-Version: 2.1
Name: matrepr
Version: 1.0.1
Summary: Format matrices and tensors to HTML, string, and LaTeX, with Jupyter integration.
Author: Adam Lugowski
Project-URL: homepage, https://github.com/alugowski/matrepr
Project-URL: repository, https://github.com/alugowski/matrepr
Keywords: matrix,tensor,sparse,html,latex,representation,table,numpy,scipy,pydata,graphblas,torch,pytorch,tensorflow
Classifier: Development Status :: 5 - Production/Stable
Classifier: Intended Audience :: Science/Research
Classifier: Intended Audience :: Developers
Classifier: License :: OSI Approved :: BSD License
Classifier: Programming Language :: Python :: 3 :: Only
Classifier: Topic :: Software Development :: Libraries
Classifier: Topic :: Scientific/Engineering
Requires-Python: >=3.7
License-File: LICENSE.txt
Requires-Dist: tabulate
Provides-Extra: supported
Requires-Dist: scipy ; extra == 'supported'
Requires-Dist: numpy ; extra == 'supported'
Requires-Dist: python-graphblas ; extra == 'supported'
Requires-Dist: sparse ; extra == 'supported'
Requires-Dist: torch >=2.0.0 ; extra == 'supported'
Requires-Dist: tensorflow ; extra == 'supported'
Provides-Extra: test
Requires-Dist: pytest ; extra == 'test'
Requires-Dist: html5lib ; extra == 'test'
Requires-Dist: scipy ; extra == 'test'
